{
    "dev": {
        "awscloudformation": {
            "AuthRoleName": "amplify-mkping-dev-205929-authRole",
            "UnauthRoleArn": "arn:aws:iam::163011916086:role/amplify-mkping-dev-205929-unauthRole",
            "AuthRoleArn": "arn:aws:iam::163011916086:role/amplify-mkping-dev-205929-authRole",
            "Region": "us-east-1",
            "DeploymentBucketName": "amplify-mkping-dev-205929-deployment",
            "UnauthRoleName": "amplify-mkping-dev-205929-unauthRole",
            "StackName": "amplify-mkping-dev-205929",
            "StackId": "arn:aws:cloudformation:us-east-1:163011916086:stack/amplify-mkping-dev-205929/3a0f3460-efdc-11ea-a8ba-121b03ae900d",
            "AmplifyAppId": "d8es3w3okkh0z"
        },
        "categories": {
            "auth": {
                "mkping5bf7600c": {}
            }
        }
    }
}